test_package/__init__.py
test_package/thecode.py
jseb_hello_world-0.0.1.dist-info/METADATA
jseb_hello_world-0.0.1.dist-info/WHEEL
jseb_hello_world-0.0.1.dist-info/top_level.txt
jseb_hello_world-0.0.1.dist-info/RECORD
