Metadata-Version: 2.1
Name: jseb-hello-world
Version: 0.0.1
Summary: This is just a test
Home-page: UNKNOWN
Author: jsebdev
Author-email: <jsebdev@gmail.com>
License: UNKNOWN
Keywords: python
Platform: UNKNOWN
Classifier: Development Status :: 1 - Planning
Classifier: Intended Audience :: Developers
Classifier: Programming Language :: Python :: 3
Classifier: Operating System :: Unix
Classifier: Operating System :: MacOS :: MacOS X
Classifier: Operating System :: Microsoft :: Windows
